zyx/__init__.py
zyx/client.py
zyx/lib/__init__.py
zyx/lib/router/__init__.py
zyx/lib/router/_router.py
zyx/lib/router/agents/__init__.py
zyx/lib/router/agents/__init__.pyi
zyx/lib/router/data/__init__.py
zyx/lib/router/data/__init__.pyi
zyx/lib/router/ext/__init__.py
zyx/lib/router/ext/__init__.pyi
zyx/lib/router/llm/__init__.py
zyx/lib/router/llm/__init__.pyi
zyx/lib/types/__init__.py
zyx/lib/types/base_model.py
zyx/lib/types/document.py
zyx/lib/utils/__init__.py
zyx/lib/utils/convert_to_openai_tool.py
zyx/lib/utils/logger.py
zyx/resources/__init__.py
zyx/resources/completions/__init__.py
zyx/resources/completions/agents/__init__.py
zyx/resources/completions/agents/conversation.py
zyx/resources/completions/agents/judge.py
zyx/resources/completions/agents/plan.py
zyx/resources/completions/agents/query.py
zyx/resources/completions/agents/scrape.py
zyx/resources/completions/agents/solve.py
zyx/resources/completions/base/__init__.py
zyx/resources/completions/base/classify.py
zyx/resources/completions/base/code.py
zyx/resources/completions/base/extract.py
zyx/resources/completions/base/function.py
zyx/resources/completions/base/generate.py
zyx/resources/completions/base/system_prompt.py
zyx/resources/data/__init__.py
zyx/resources/data/chunk.py
zyx/resources/data/reader.py
zyx/resources/ext/__init__.py
zyx/resources/ext/app.py
zyx/resources/ext/multimodal.py
zyx/resources/stores/__init__.py
zyx/resources/stores/memory.py
zyx/resources/tools/__init__.py
zyx/resources/tools/execute_code.py
zyx/resources/tools/generate_audio.py
zyx/resources/tools/generate_image.py
zyx/resources/tools/web_search.py
zyx/resources/tools/write_file.py
zyx-1.0.16.dist-info/METADATA
zyx-1.0.16.dist-info/WHEEL
zyx-1.0.16.dist-info/entry_points.txt
zyx-1.0.16.dist-info/RECORD
