Metadata-Version: 2.1
Name: zyx
Version: 1.0.16
Summary: A hyper-fast, fun, quality-of-life focused & genuinely useful LLM toolkit. Inspired by Marvin-AI. Built on LiteLLM, Instructor & Qdrant.
Author: Hammad Saeed
Author-email: hvmmad@gmail.com
Requires-Python: >=3.10,<4.0
Classifier: Programming Language :: Python :: 3
Classifier: Programming Language :: Python :: 3.10
Classifier: Programming Language :: Python :: 3.11
Classifier: Programming Language :: Python :: 3.12
Provides-Extra: data
Requires-Dist: bs4 (>=0.0.2,<0.0.3) ; extra == "data"
Requires-Dist: chromadb (>=0.5.11,<0.6.0) ; extra == "data"
Requires-Dist: duckduckgo-search (>=6.2.13,<7.0.0) ; extra == "data"
Requires-Dist: instructor (>=1.4.2,<2.0.0)
Requires-Dist: litellm (>=1.46.5,<2.0.0)
Requires-Dist: openpyxl (>=3.1.5,<4.0.0) ; extra == "data"
Requires-Dist: pydub (>=0.25.1,<0.26.0)
Requires-Dist: pypdf2 (>=3.0.1,<4.0.0) ; extra == "data"
Requires-Dist: python-docx (>=1.1.2,<2.0.0) ; extra == "data"
Requires-Dist: rich (>=13.8.1,<14.0.0)
Requires-Dist: semchunk (>=2.2.0,<3.0.0) ; extra == "data"
Requires-Dist: sounddevice (>=0.5.0,<0.6.0)
Requires-Dist: soundfile (>=0.12.1,<0.13.0)
Requires-Dist: textual (>=0.79.1,<0.80.0)
